Workbook

Sheet Read me
A1: TrueNorth Growth Scoreboard
A2: One number decides every marketing choice: what it costs to sign one door (property), compared with what a door is worth.
A4: How to read the colors
A5: Blue text = an input you type or change. Black text = a formula (don't overwrite). Yellow fill = a key assumption to confirm with your own numbers.
A7: Tabs
A8: Door Economics — what one door earns per year and over its life, the most you can spend to win one, doors needed for your income goal, and a postcard calculator.
A9: Weekly Scoreboard — fill one row every Monday (about 5 minutes). The grey 'Example' row shows the format and is excluded from totals.
A10: Channels — spend, leads, and signed doors per channel. Cost per door is compared against the maximum from Door Economics.
A12: Where the numbers come from
A13: Leads: every website lead email now ends with its channel in [brackets], e.g. [postcard / direct_mail], [google_business_profile / organic], [direct].
A14: Spend: postcard invoices, ad platform billing, printing. Reviews: your Google Business Profile. Doors: signed management agreements.
A16: Starting values are placeholders from the website's 'starting at' pricing and common planning assumptions — replace them with your real figures.

Sheet Door Economics
A1: Door Economics
A2: What one managed property (door) is worth, and what you can afford to spend to win one.
A4: Inputs
A5: Average monthly management fee ($) | B5: 149 | C5: Plus plan 'starting at' price on the website (src/lib/pricing.ts). Use your real average.
A6: Average monthly rent ($) | B6: 2200 | C6: Example Spring Hill single-family rent. Replace with your portfolio average.
A7: Leasing fee (share of one month's rent) | B7: 0.75 | C7: Leasing 'starting at' 75% of first month (website). Confirm Exhibit B line 3.
A8: Tenant turnover rate (per year) | B8: 0.5 | C8: Assumption: 50% = a new tenant about every 2 years.
A9: Renewal fee ($) | B9: 299 | C9: Renewal 'starting at' $299 (website). Charged in years without turnover.
A10: Direct cost per door ($ per year) | B10: 300 | C10: Assumption: software, mileage, supplies per door. Replace with actuals.
A11: Average years an owner stays | B11: 3.5 | C11: Assumption. Retention is the biggest lever on lifetime value.
A12: Max share of lifetime contribution to spend winning a door | B12: 0.2 | C12: Assumption: keep acquisition cost at or under 20% of lifetime contribution.
A13: Owner income goal ($ per year) | B13: 100000 | C13: Your target take-home before tax.
A14: Fixed overhead ($ per year) | B14: 12000 | C14: Assumption: E&O and liability insurance, licenses, software base fees, baseline marketing.
A16: Per-door results
A17: Management fees per door per year | B17: =B5*12
A18: Leasing fees per door per year | B18: =B6*B7*B8 | C18: Rent x leasing % x how often a new tenant is placed.
A19: Renewal fees per door per year | B19: =B9*(1-B8) | C19: Renewal fee in the years the tenant stays.
A20: Revenue per door per year | B20: =SUM(B17:B19)
A21: Contribution per door per year | B21: =B20-B10 | C21: Revenue minus direct cost.
A22: Lifetime contribution per door | B22: =B21*B11
A23: Max you can spend to win one door | B23: =B22*B12 | C23: Compare every channel's cost per door to this (Channels tab).
A25: Scale
A26: Doors needed for your income goal | B26: =IF(B21>0,ROUNDUP((B13+B14)/B21,0),"-") | C26: (Income goal + overhead) / contribution per door.
A27: Annual revenue at that door count | B27: =IF(ISNUMBER(B26),B26*B20,"-")
A29: Postcard calculator
A30: Postcards mailed | B30: 1000 | C30: One drop to the absentee-owner list.
A31: All-in cost per postcard (print + postage + list) | B31: 0.75 | C31: Assumption: 6x9 marketing mail commonly lands around $0.60–$1.00 all-in. Get a vendor quote.
A32: Response rate (leads per postcard) | B32: 0.01 | C32: Assumption: 0.5%–1.5% is a common planning range; repeat drops usually respond better.
A33: Lead-to-signed-door rate | B33: 0.2 | C33: Assumption: 1 in 5 owners who request an analysis signs.
A34: Total mail cost | B34: =B30*B31
A35: Leads expected | B35: =B30*B32
A36: Doors expected | B36: =B35*B33
A37: Cost per door from postcards | B37: =IF(B36>0,B34/B36,"-")
A38: Worth it? | B38: =IF(ISNUMBER(B37),IF(B37<=B23,"Yes: under your max cost per door","No: improve the list, offer, or follow-up"),"-")

Sheet Weekly Scoreboard
A1: Weekly Scoreboard
A2: Fill one row every Monday. Blue cells are yours; black columns calculate.
A4: Week of | B4: Website leads | C4: Rental analyses sent | D4: Consults booked | E4: Agreements signed | F4: Doors added | G4: Total doors | H4: Google reviews (total) | I4: Median reply time (hrs) | J4: Marketing spend ($) | K4: Spend to date ($) | L4: Cost per door to date ($)
A5: Example | B5: 6 | C5: 5 | D5: 3 | E5: 1 | F5: 1 | G5: =F5 | H5: 4 | I5: 2 | J5: 250 | K5: =J5 | L5: =IF(G5>0,K5/G5,"-")
A6: 46279 | G6: =F6 | K6: =J6 | L6: =IF(G6>0,K6/G6,"-")
A7: =A6+7 | G7: =G6+F7 | K7: =K6+J7 | L7: =IF(G7>0,K7/G7,"-")
A8: =A7+7 | G8: =G7+F8 | K8: =K7+J8 | L8: =IF(G8>0,K8/G8,"-")
A9: =A8+7 | G9: =G8+F9 | K9: =K8+J9 | L9: =IF(G9>0,K9/G9,"-")
A10: =A9+7 | G10: =G9+F10 | K10: =K9+J10 | L10: =IF(G10>0,K10/G10,"-")
A11: =A10+7 | G11: =G10+F11 | K11: =K10+J11 | L11: =IF(G11>0,K11/G11,"-")
A12: =A11+7 | G12: =G11+F12 | K12: =K11+J12 | L12: =IF(G12>0,K12/G12,"-")
A13: =A12+7 | G13: =G12+F13 | K13: =K12+J13 | L13: =IF(G13>0,K13/G13,"-")
A14: =A13+7 | G14: =G13+F14 | K14: =K13+J14 | L14: =IF(G14>0,K14/G14,"-")
A15: =A14+7 | G15: =G14+F15 | K15: =K14+J15 | L15: =IF(G15>0,K15/G15,"-")
A16: =A15+7 | G16: =G15+F16 | K16: =K15+J16 | L16: =IF(G16>0,K16/G16,"-")
A17: =A16+7 | G17: =G16+F17 | K17: =K16+J17 | L17: =IF(G17>0,K17/G17,"-")
A18: =A17+7 | G18: =G17+F18 | K18: =K17+J18 | L18: =IF(G18>0,K18/G18,"-")
A19: 13-week total | B19: =SUM(B6:B18) | C19: =SUM(C6:C18) | D19: =SUM(D6:D18) | E19: =SUM(E6:E18) | F19: =SUM(F6:F18) | G19: =G18 | H19: =MAX(H6:H18) | I19: =IF(COUNT(I6:I18)>0,MEDIAN(I6:I18),"-") | J19: =SUM(J6:J18) | K19: =K18 | L19: =IF(G19>0,K19/G19,"-")
A21: Targets for the first 90 days: reply to every lead within 1 hour on business days; 10+ Google reviews; cost per door under the max on Door Economics.

Sheet Channels
A1: Channels
A2: Keep a running total per channel. Status compares cost per door with the max on Door Economics.
A4: Channel | B4: Spend ($) | C4: Leads | D4: Consults | E4: Signed doors | F4: Cost per lead ($) | G4: Cost per door ($) | H4: Lead → door rate | I4: Status | J4: Lead email tag
A5: Google Business Profile | F5: =IF(C5>0,B5/C5,"-") | G5: =IF(E5>0,B5/E5,"-") | H5: =IF(C5>0,E5/C5,"-") | I5: =IF(E5=0,IF(B5>0,"No doors yet","-"),IF(B5/E5<='Door Economics'!$B$23,"Scale up","Fix or cut")) | J5: google_business_profile / organic
A6: Postcards (absentee owners) | F6: =IF(C6>0,B6/C6,"-") | G6: =IF(E6>0,B6/E6,"-") | H6: =IF(C6>0,E6/C6,"-") | I6: =IF(E6=0,IF(B6>0,"No doors yet","-"),IF(B6/E6<='Door Economics'!$B$23,"Scale up","Fix or cut")) | J6: postcard / direct_mail
A7: Agent referrals | F7: =IF(C7>0,B7/C7,"-") | G7: =IF(E7>0,B7/E7,"-") | H7: =IF(C7>0,E7/C7,"-") | I7: =IF(E7=0,IF(B7>0,"No doors yet","-"),IF(B7/E7<='Door Economics'!$B$23,"Scale up","Fix or cut")) | J7: agent_onepager / print
A8: Switch outreach | F8: =IF(C8>0,B8/C8,"-") | G8: =IF(E8>0,B8/E8,"-") | H8: =IF(C8>0,E8/C8,"-") | I8: =IF(E8=0,IF(B8>0,"No doors yet","-"),IF(B8/E8<='Door Economics'!$B$23,"Scale up","Fix or cut")) | J8: outreach / offline
A9: Social media (organic) | F9: =IF(C9>0,B9/C9,"-") | G9: =IF(E9>0,B9/E9,"-") | H9: =IF(C9>0,E9/C9,"-") | I9: =IF(E9=0,IF(B9>0,"No doors yet","-"),IF(B9/E9<='Door Economics'!$B$23,"Scale up","Fix or cut")) | J9: facebook.com, instagram.com, linkedin.com
A10: Google Ads | F10: =IF(C10>0,B10/C10,"-") | G10: =IF(E10>0,B10/E10,"-") | H10: =IF(C10>0,E10/C10,"-") | I10: =IF(E10=0,IF(B10>0,"No doors yet","-"),IF(B10/E10<='Door Economics'!$B$23,"Scale up","Fix or cut")) | J10: google ads
A11: Meta Ads | F11: =IF(C11>0,B11/C11,"-") | G11: =IF(E11>0,B11/E11,"-") | H11: =IF(C11>0,E11/C11,"-") | I11: =IF(E11=0,IF(B11>0,"No doors yet","-"),IF(B11/E11<='Door Economics'!$B$23,"Scale up","Fix or cut")) | J11: meta
A12: Website / SEO | F12: =IF(C12>0,B12/C12,"-") | G12: =IF(E12>0,B12/E12,"-") | H12: =IF(C12>0,E12/C12,"-") | I12: =IF(E12=0,IF(B12>0,"No doors yet","-"),IF(B12/E12<='Door Economics'!$B$23,"Scale up","Fix or cut")) | J12: google.com, bing.com
A13: Word of mouth / direct | F13: =IF(C13>0,B13/C13,"-") | G13: =IF(E13>0,B13/E13,"-") | H13: =IF(C13>0,E13/C13,"-") | I13: =IF(E13=0,IF(B13>0,"No doors yet","-"),IF(B13/E13<='Door Economics'!$B$23,"Scale up","Fix or cut")) | J13: direct
A14: Total | B14: =SUM(B5:B13) | C14: =SUM(C5:C13) | D14: =SUM(D5:D13) | E14: =SUM(E5:E13) | F14: =IF(C14>0,B14/C14,"-") | G14: =IF(E14>0,B14/E14,"-") | H14: =IF(C14>0,E14/C14,"-")
